src/main/resources/tempFiles/verilog/project1/trasmission.v
module jtransmissiongate(y,control,a);
	output y;
	input a,control;
	
	wire cbar;
	
	assign cbar = ~control;
	
	nmos n1(y,a,control);
	pmos p1(y,a,cbar);
	//cmos c1(y,a,control,cbar);
	
endmodule

src/main/resources/tempFiles/verilog/project1/trasmissionTb.v
module jtransmissiongatetb;
	wire y;
	reg a,control;
	jtransmissiongate jtgate(y,control,a);
	initial
	begin
		$display ("RESULT\ta\ty");

		a = 0; control = 0; # 50; // Initial value is set
		if ( y === 1'bz ) // Test for inversion
			$display ("PASS  \t%d\t%d",a,y);
		else
			$display ("FAIL  \t%d\t%d",a,y);
		control = 1; # 50; // Simply change the control signal
		control = 0; # 50; // Simply change the control signal
		control = 1; # 50; // Simply change the control signal
		control = 0; # 50; // Simply change the control signal

		a = 0; control = 1; # 50; // Initial value is set
		if ( y === 0 ) // Test for inversion
			$display ("PASS  \t%d\t%d",a,y);
		else
			$display ("FAIL  \t%d\t%d",a,y);

		a = 1; control = 0; # 50; // Another value
		if ( y === 1'bz ) // Test for inversion
			$display ("PASS  \t%d\t%d",a,y);
		else
			$display ("FAIL  \t%d\t%d",a,y);
		control = 1; # 50; // Simply change the control signal
		control = 0; # 50; // Simply change the control signal
		control = 1; # 50; // Simply change the control signal
		control = 0; # 50; // Simply change the control signal

		a = 1; control = 1; # 50; // Another value
		if ( y === 1 ) // Test for inversion
			$display ("PASS  \t%d\t%d",a,y);
		else
			$display ("FAIL  \t%d\t%d",a,y);

	end

  
  initial
    begin
      $dumpfile("/home/flugel/personal/programs/git/OpenVerilog/src/main/resources/bin/datadump/dump.vcd");
      $dumpvars(0,jtransmissiongatetb);
    end
endmodule

src/main/resources/bin/datadump/dump.vcd
$date
	Tue Feb 11 16:22:14 2025
$end
$version
	Icarus Verilog
$end
$timescale
	1s
$end
$scope module jtransmissiongatetb $end
$var wire 1 ! y $end
$var reg 1 " a $end
$var reg 1 # control $end
$scope module jtgate $end
$var wire 1 " a $end
$var wire 1 $ cbar $end
$var wire 1 # control $end
$var wire 1 ! y $end
$upscope $end
$upscope $end
$enddefinitions $end
$comment Show the parameter values. $end
$dumpall
$end
#0
$dumpvars
1$
0#
0"
z!
$end
#50
0$
0!
1#
#100
z!
1$
0#
#150
0$
0!
1#
#200
z!
1$
0#
#250
0$
0!
1#
#300
1$
0#
z!
1"
#350
0$
1!
1#
#400
z!
1$
0#
#450
0$
1!
1#
#500
z!
1$
0#
#550
0$
1!
1#
